groups_local/__init__.py
groups_local/groups_local.py
groups_local/groups_local_constants.py
groups_local-0.0.12.dist-info/METADATA
groups_local-0.0.12.dist-info/WHEEL
groups_local-0.0.12.dist-info/top_level.txt
groups_local-0.0.12.dist-info/RECORD
