Metadata-Version: 2.1
Name: groups-local
Version: 0.0.12
Summary: PyPI Package for Circles groups-local Python
Home-page: https://github.com/circles-zone/group-main-local-python-package
Author: Circles
Author-email: info@circles.life
Classifier: Programming Language :: Python :: 3
Classifier: License :: Other/Proprietary License
Classifier: Operating System :: OS Independent
Requires-Dist: PyMySQL >=1.0.2
Requires-Dist: pytest >=7.4.0
Requires-Dist: mysql-connector >=2.2.9
Requires-Dist: logzio-python-handler >=4.1.0
Requires-Dist: database-infrastructure-local >=0.0.23
Requires-Dist: user-context-remote >=0.0.58
